[
    {
        "CustomerID": "2521030014",
        "FirstName": "Xiaomi",
        "LastName": "King",
        "Birthday": "2004-05-10T14:23:00",
        "Gender": "M",
        "StreetName": "Pink Avenue",
        "HouseNumber": "576",
        "ZipCode": "3697WR",
        "City": "Roosendaal",
        "Email": "xiaomi@outlook.com",
        "PhoneNumber": "+31-6-12345678",
        "DrivingLicenseNumber": "AB1234567",
        "RegistrationDate": "2024-05-10T14:23:00"
    },
    {
        "CustomerID": "2588503102",
        "FirstName": "Hannah",
        "LastName": "Pet",
        "Birthday": "1994-10-11T14:23:00",
        "Gender": "F",
        "StreetName": "Bouwgaarweg",
        "HouseNumber": "12A",
        "ZipCode": "2586QE",
        "City": "Rotterdam",
        "Email": "hannah@outlook.com",
        "PhoneNumber": "+31-6-87654321",
        "DrivingLicenseNumber": "CD7654321",
        "RegistrationDate": "2024-05-10T14:23:00"
    },
    {
        "CustomerID": "2537698886",
        "FirstName": "Chorouk",
        "LastName": "Cherry",
        "Birthday": "2003-02-07T14:23:00",
        "Gender": "F",
        "StreetName": "KittyLane",
        "HouseNumber": "777",
        "ZipCode": "1475PO",
        "City": "Nijmegen",
        "Email": "cherry@outlook.com",
        "PhoneNumber": "+31-6-11223344",
        "DrivingLicenseNumber": "E98765432",
        "RegistrationDate": "2024-05-10T14:23:00"
    },
    {
        "CustomerID": "2512938707",
        "FirstName": "Dilara",
        "LastName": "Azul",
        "Birthday": "2001-08-08T14:23:00",
        "Gender": "F",
        "StreetName": "Lightningbaan",
        "HouseNumber": "918",
        "ZipCode": "0274AA",
        "City": "Vienna",
        "Email": "dilara@outlook.com",
        "PhoneNumber": "+31-6-92735548",
        "DrivingLicenseNumber": "D92735548",
        "RegistrationDate": "2024-05-10T14:23:00"
    },
    {
        "CustomerID": "2550075059",
        "FirstName": "Lucy",
        "LastName": "Daisy",
        "Birthday": "2003-11-11T14:23:00",
        "Gender": "F",
        "StreetName": "DuckDuck Lane",
        "HouseNumber": "111",
        "ZipCode": "1111LU",
        "City": "Linköping",
        "Email": "lucy@outlook.com",
        "PhoneNumber": "+31-6-00001111",
        "DrivingLicenseNumber": "LU1029384",
        "RegistrationDate": "2024-05-10T14:23:00"
    }
]